ironcalc/__init__.py
ironcalc/ironcalc.cpython-312-darwin.so
ironcalc-0.7.0.dist-info/METADATA
ironcalc-0.7.0.dist-info/WHEEL
ironcalc-0.7.0.dist-info/licenses/LICENSE-Apache-2.0.md
ironcalc-0.7.0.dist-info/licenses/LICENSE-MIT.md
ironcalc-0.7.0.dist-info/RECORD
