Metadata-Version: 2.4
Name: ironcalc
Version: 0.7.0
Classifier: License :: OSI Approved :: MIT License
Classifier: License :: OSI Approved :: Apache Software License
Classifier: Development Status :: 3 - Alpha
Classifier: Intended Audience :: Developers
Classifier: Operating System :: OS Independent
Classifier: Programming Language :: Python :: 3
Classifier: Topic :: Software Development :: Libraries
Classifier: Topic :: Software Development :: Libraries :: Python Modules
Classifier: Topic :: Office/Business :: Financial :: Spreadsheet
License-File: LICENSE-Apache-2.0.md
License-File: LICENSE-MIT.md
Summary: Create, edit and evaluate Excel spreadsheets
Keywords: xlsx,spreadsheet
Author-email: Nicolás Hatcher <nicolas@theuniverse.today>
Requires-Python: >=3.10
Project-URL: Homepage, https://www.ironcalc.com/
Project-URL: Source, https://github.com/ironcalc/ironcalc
Project-URL: Tracker, https://github.com/ironcalc/ironcalc/issues
